cdktf_cdktf_provider_yandex/__init__.py
cdktf_cdktf_provider_yandex/py.typed
cdktf_cdktf_provider_yandex/_jsii/__init__.py
cdktf_cdktf_provider_yandex/_jsii/provider-yandex@2.0.32.jsii.tgz
cdktf_cdktf_provider_yandex-2.0.32.dist-info/LICENSE
cdktf_cdktf_provider_yandex-2.0.32.dist-info/METADATA
cdktf_cdktf_provider_yandex-2.0.32.dist-info/WHEEL
cdktf_cdktf_provider_yandex-2.0.32.dist-info/top_level.txt
cdktf_cdktf_provider_yandex-2.0.32.dist-info/RECORD
