Metadata-Version: 2.1
Name: cdktf-cdktf-provider-yandex
Version: 2.0.32
Summary: Prebuilt yandex Provider for Terraform CDK (cdktf)
Home-page: https://github.com/hashicorp/cdktf-provider-yandex.git
Author: HashiCorp
License: MPL-2.0
Project-URL: Source, https://github.com/hashicorp/cdktf-provider-yandex.git
Classifier: Intended Audience :: Developers
Classifier: Operating System :: OS Independent
Classifier: Programming Language :: JavaScript
Classifier: Programming Language :: Python :: 3 :: Only
Classifier: Programming Language :: Python :: 3.7
Classifier: Programming Language :: Python :: 3.8
Classifier: Programming Language :: Python :: 3.9
Classifier: Programming Language :: Python :: 3.10
Classifier: Typing :: Typed
Classifier: Development Status :: 5 - Production/Stable
Classifier: License :: OSI Approved
Requires-Python: ~=3.7
License-File: LICENSE
Requires-Dist: cdktf (<0.13.0,>=0.12.0)
Requires-Dist: constructs (<11.0.0,>=10.0.0)
Requires-Dist: jsii (<2.0.0,>=1.65.0)
Requires-Dist: publication (>=0.0.3)
Requires-Dist: typeguard (~=2.13.3)
